bijoy2unicode.py
bijoytounicode.py
bijoy2unicode/__init__.py
bijoy2unicode/bijoy2unicode.py
tests/__init__.py
tests/test.py
bijoytounicode-1.1.1.dist-info/LICENSE
bijoytounicode-1.1.1.dist-info/METADATA
bijoytounicode-1.1.1.dist-info/WHEEL
bijoytounicode-1.1.1.dist-info/top_level.txt
bijoytounicode-1.1.1.dist-info/RECORD
