Metadata-Version: 2.1
Name: bijoytounicode
Version: 1.1.1
Summary: A Bijoy to Unicode converter utility for Python.
Home-page: https://gitlab.com/codesigntheory/bijoytounicode
Author: Utsob Roy
Author-email: roy@codesign.com.bd
License: UNKNOWN
Keywords: Bijoy Unicode Converter
Platform: UNKNOWN
Classifier: Programming Language :: Python :: 3
Classifier: License :: OSI Approved :: Mozilla Public License 2.0 (MPL 2.0)
Classifier: Topic :: Software Development :: Libraries
Classifier: Topic :: Text Processing :: Linguistic
